rs_audio_playrec-0.1.1.dist-info/METADATA
rs_audio_playrec-0.1.1.dist-info/WHEEL
rs_audio_playrec/__init__.py
rs_audio_playrec/_rs_audio_playrec.cp310-win_amd64.pyd
rs_audio_playrec-0.1.1.dist-info/RECORD
