Metadata-Version: 2.4
Name: rs-audio-playrec
Version: 0.1.1
Classifier: Development Status :: 3 - Alpha
Classifier: Intended Audience :: Developers
Classifier: License :: OSI Approved :: MIT License
Classifier: Programming Language :: Python :: 3
Classifier: Programming Language :: Python :: 3.10
Classifier: Programming Language :: Python :: 3.11
Classifier: Programming Language :: Python :: 3.12
Classifier: Programming Language :: Rust
Classifier: Topic :: Multimedia :: Sound/Audio
Classifier: Topic :: Software Development :: Libraries :: Python Modules
Summary: High-performance audio playback and recording library
Author-email: hiroshi-tamura <your-email@example.com>
License: MIT
Requires-Python: >=3.10
Project-URL: Homepage, https://github.com/hiroshi-tamura/rs_audio_playrec
Project-URL: Repository, https://github.com/hiroshi-tamura/rs_audio_playrec
Project-URL: Issues, https://github.com/hiroshi-tamura/rs_audio_playrec/issues
